CHANGES.txt
LICENSE.txt
README.txt
bootstrap.py
setup.py
src/z3c/__init__.py
src/z3c.indexer.egg-info/PKG-INFO
src/z3c.indexer.egg-info/SOURCES.txt
src/z3c.indexer.egg-info/dependency_links.txt
src/z3c.indexer.egg-info/namespace_packages.txt
src/z3c.indexer.egg-info/not-zip-safe
src/z3c.indexer.egg-info/requires.txt
src/z3c.indexer.egg-info/top_level.txt
src/z3c/indexer/README.txt
src/z3c/indexer/__init__.py
src/z3c/indexer/_bbb.py
src/z3c/indexer/collector.py
src/z3c/indexer/index.py
src/z3c/indexer/indexer.py
src/z3c/indexer/interfaces.py
src/z3c/indexer/performance.py
src/z3c/indexer/query.py
src/z3c/indexer/sample.txt
src/z3c/indexer/search.py
src/z3c/indexer/subscriber.py
src/z3c/indexer/subscriber.zcml
src/z3c/indexer/testing.py
src/z3c/indexer/tests.py